segment_anything_utils/__init__.py
segment_anything_utils/load.py
segment_anything_utils-0.2.1.dist-info/METADATA
segment_anything_utils-0.2.1.dist-info/WHEEL
segment_anything_utils-0.2.1.dist-info/top_level.txt
segment_anything_utils-0.2.1.dist-info/RECORD
