Metadata-Version: 2.1
Name: segment-anything-utils
Version: 0.2.1
Summary: utils for segment_anything.
Home-page: https://github.com/tomdyqin/segment-anything-utils
Author: Tomdy Qin
Author-email: tomdyqin@qq.com
License: MIT
Classifier: License :: OSI Approved :: MIT License
Classifier: Programming Language :: Python
Classifier: Programming Language :: Python :: 3
Classifier: Programming Language :: Python :: 3.6
Classifier: Programming Language :: Python :: Implementation :: CPython
Classifier: Programming Language :: Python :: Implementation :: PyPy
Requires-Python: >=3.6.0
Requires-Dist: requests
Requires-Dist: importlib
Requires-Dist: tqdm
Requires-Dist: torch
Requires-Dist: segment-anything
